sqlanalyzer/__init__.py
sqlanalyzer/column_parser.py
sqlanalyzer/main_script.py
sqlanalyzer/query_analyzer.py
sqlanalyzer/unbundle.py
sqlanalyzer/unnest_query.py
sqlanalyzer-0.6.0.dist-info/LICENSE
sqlanalyzer-0.6.0.dist-info/METADATA
sqlanalyzer-0.6.0.dist-info/WHEEL
sqlanalyzer-0.6.0.dist-info/top_level.txt
sqlanalyzer-0.6.0.dist-info/RECORD
